{"name":"build-javascript","namedChunkGroups":{"polyfill":{"name":"polyfill","assets":[{"name":"webpack-runtime-5835002e30f4e0072ca2.js","size":4189},{"name":"polyfill-f4411e3462bda6c5a4fc.js","size":100878}],"filteredAssets":0,"assetsSize":105067,"filteredAuxiliaryAssets":2,"auxiliaryAssetsSize":297587},"app":{"name":"app","assets":[{"name":"webpack-runtime-5835002e30f4e0072ca2.js","size":4189},{"name":"framework-b9d19da071885309f779.js","size":129757},{"name":"styles.5255380b58e9eef723c6.css","size":19776},{"name":"app-4a43675c19d7115e46f9.js","size":134731}],"filteredAssets":0,"assetsSize":288453,"filteredAuxiliaryAssets":55,"auxiliaryAssetsSize":1957123},"component---src-pages-404-tsx":{"name":"component---src-pages-404-tsx","assets":[{"name":"cb1608f2-132bad9b5b9e5b660256.js","size":905},{"name":"a9a7754c-940be9729966a77c2e4e.js","size":2470},{"name":"commons-a6bfc7d3adecb3157ef4.js","size":20604},{"name":"component---src-pages-404-tsx-8351a3379b9131fdea4e.js","size":744}],"filteredAssets":0,"assetsSize":24723,"filteredAuxiliaryAssets":4,"auxiliaryAssetsSize":1571841},"component---src-pages-index-tsx":{"name":"component---src-pages-index-tsx","assets":[{"name":"cb1608f2-132bad9b5b9e5b660256.js","size":905},{"name":"a9a7754c-940be9729966a77c2e4e.js","size":2470},{"name":"commons-a6bfc7d3adecb3157ef4.js","size":20604},{"name":"component---src-pages-index-tsx-ae5fa1fadc7688ca165e.js","size":841}],"filteredAssets":0,"assetsSize":24820,"filteredAuxiliaryAssets":4,"auxiliaryAssetsSize":1572429},"component---src-pages-tags-tsx":{"name":"component---src-pages-tags-tsx","assets":[{"name":"cb1608f2-132bad9b5b9e5b660256.js","size":905},{"name":"a9a7754c-940be9729966a77c2e4e.js","size":2470},{"name":"commons-a6bfc7d3adecb3157ef4.js","size":20604},{"name":"component---src-pages-tags-tsx-d8419ed56495cc3ef067.js","size":797}],"filteredAssets":0,"assetsSize":24776,"filteredAuxiliaryAssets":4,"auxiliaryAssetsSize":1572356},"component---src-templates-blog-post-tsx":{"name":"component---src-templates-blog-post-tsx","assets":[{"name":"cb1608f2-132bad9b5b9e5b660256.js","size":905},{"name":"a9a7754c-940be9729966a77c2e4e.js","size":2470},{"name":"commons-a6bfc7d3adecb3157ef4.js","size":20604},{"name":"component---src-templates-blog-post-tsx-841b1fde5b6d7ea71387.js","size":12010}],"filteredAssets":0,"assetsSize":35989,"filteredAuxiliaryAssets":4,"auxiliaryAssetsSize":1609509},"component---src-templates-blog-tag-tsx":{"name":"component---src-templates-blog-tag-tsx","assets":[{"name":"cb1608f2-132bad9b5b9e5b660256.js","size":905},{"name":"a9a7754c-940be9729966a77c2e4e.js","size":2470},{"name":"commons-a6bfc7d3adecb3157ef4.js","size":20604},{"name":"component---src-templates-blog-tag-tsx-e0373b4c44a306e77eeb.js","size":879}],"filteredAssets":0,"assetsSize":24858,"filteredAuxiliaryAssets":4,"auxiliaryAssetsSize":1572760}},"assetsByChunkName":{"polyfill":["webpack-runtime-5835002e30f4e0072ca2.js","polyfill-f4411e3462bda6c5a4fc.js"],"app":["webpack-runtime-5835002e30f4e0072ca2.js","framework-b9d19da071885309f779.js","styles.5255380b58e9eef723c6.css","app-4a43675c19d7115e46f9.js"],"component---src-pages-404-tsx":["cb1608f2-132bad9b5b9e5b660256.js","a9a7754c-940be9729966a77c2e4e.js","commons-a6bfc7d3adecb3157ef4.js","component---src-pages-404-tsx-8351a3379b9131fdea4e.js"],"component---src-pages-index-tsx":["cb1608f2-132bad9b5b9e5b660256.js","a9a7754c-940be9729966a77c2e4e.js","commons-a6bfc7d3adecb3157ef4.js","component---src-pages-index-tsx-ae5fa1fadc7688ca165e.js"],"component---src-pages-tags-tsx":["cb1608f2-132bad9b5b9e5b660256.js","a9a7754c-940be9729966a77c2e4e.js","commons-a6bfc7d3adecb3157ef4.js","component---src-pages-tags-tsx-d8419ed56495cc3ef067.js"],"component---src-templates-blog-post-tsx":["cb1608f2-132bad9b5b9e5b660256.js","a9a7754c-940be9729966a77c2e4e.js","commons-a6bfc7d3adecb3157ef4.js","component---src-templates-blog-post-tsx-841b1fde5b6d7ea71387.js"],"component---src-templates-blog-tag-tsx":["cb1608f2-132bad9b5b9e5b660256.js","a9a7754c-940be9729966a77c2e4e.js","commons-a6bfc7d3adecb3157ef4.js","component---src-templates-blog-tag-tsx-e0373b4c44a306e77eeb.js"]},"childAssetsByChunkName":{}}