{"name":"build-javascript","namedChunkGroups":{"polyfill":{"name":"polyfill","assets":[{"name":"webpack-runtime-b76f034209f5e7866361.js","size":4163},{"name":"polyfill-f4411e3462bda6c5a4fc.js","size":100878}],"filteredAssets":0,"assetsSize":105041,"filteredAuxiliaryAssets":2,"auxiliaryAssetsSize":297553},"app":{"name":"app","assets":[{"name":"webpack-runtime-b76f034209f5e7866361.js","size":4163},{"name":"framework-b9d19da071885309f779.js","size":129757},{"name":"styles.57b816a3ef2aca73b614.css","size":19776},{"name":"app-2f18b3c3e9642e1c385c.js","size":151728}],"filteredAssets":0,"assetsSize":305424,"filteredAuxiliaryAssets":55,"auxiliaryAssetsSize":2008862},"component---src-pages-404-tsx":{"name":"component---src-pages-404-tsx","assets":[{"name":"cb1608f2-132bad9b5b9e5b660256.js","size":905},{"name":"a9a7754c-940be9729966a77c2e4e.js","size":2470},{"name":"component---src-pages-404-tsx-b5ac90938baaeb05359e.js","size":6278}],"filteredAssets":0,"assetsSize":9653,"filteredAuxiliaryAssets":3,"auxiliaryAssetsSize":1806989},"component---src-pages-index-tsx":{"name":"component---src-pages-index-tsx","assets":[{"name":"cb1608f2-132bad9b5b9e5b660256.js","size":905},{"name":"a9a7754c-940be9729966a77c2e4e.js","size":2470},{"name":"component---src-pages-index-tsx-026844f65b41601042de.js","size":6375}],"filteredAssets":0,"assetsSize":9750,"filteredAuxiliaryAssets":3,"auxiliaryAssetsSize":1807587},"component---src-pages-tags-tsx":{"name":"component---src-pages-tags-tsx","assets":[{"name":"cb1608f2-132bad9b5b9e5b660256.js","size":905},{"name":"a9a7754c-940be9729966a77c2e4e.js","size":2470},{"name":"component---src-pages-tags-tsx-8725b4085ac317385e23.js","size":6348}],"filteredAssets":0,"assetsSize":9723,"filteredAuxiliaryAssets":3,"auxiliaryAssetsSize":1807530},"component---src-templates-blog-post-tsx":{"name":"component---src-templates-blog-post-tsx","assets":[{"name":"cb1608f2-132bad9b5b9e5b660256.js","size":905},{"name":"a9a7754c-940be9729966a77c2e4e.js","size":2470},{"name":"component---src-templates-blog-post-tsx-63879093293c38df465c.js","size":17583}],"filteredAssets":0,"assetsSize":20958,"filteredAuxiliaryAssets":3,"auxiliaryAssetsSize":1844907},"component---src-templates-blog-tag-tsx":{"name":"component---src-templates-blog-tag-tsx","assets":[{"name":"cb1608f2-132bad9b5b9e5b660256.js","size":905},{"name":"a9a7754c-940be9729966a77c2e4e.js","size":2470},{"name":"component---src-templates-blog-tag-tsx-f9e91ba073d8cbc40546.js","size":6413}],"filteredAssets":0,"assetsSize":9788,"filteredAuxiliaryAssets":3,"auxiliaryAssetsSize":1807902}},"assetsByChunkName":{"polyfill":["webpack-runtime-b76f034209f5e7866361.js","polyfill-f4411e3462bda6c5a4fc.js"],"app":["webpack-runtime-b76f034209f5e7866361.js","framework-b9d19da071885309f779.js","styles.57b816a3ef2aca73b614.css","app-2f18b3c3e9642e1c385c.js"],"component---src-pages-404-tsx":["cb1608f2-132bad9b5b9e5b660256.js","a9a7754c-940be9729966a77c2e4e.js","component---src-pages-404-tsx-b5ac90938baaeb05359e.js"],"component---src-pages-index-tsx":["cb1608f2-132bad9b5b9e5b660256.js","a9a7754c-940be9729966a77c2e4e.js","component---src-pages-index-tsx-026844f65b41601042de.js"],"component---src-pages-tags-tsx":["cb1608f2-132bad9b5b9e5b660256.js","a9a7754c-940be9729966a77c2e4e.js","component---src-pages-tags-tsx-8725b4085ac317385e23.js"],"component---src-templates-blog-post-tsx":["cb1608f2-132bad9b5b9e5b660256.js","a9a7754c-940be9729966a77c2e4e.js","component---src-templates-blog-post-tsx-63879093293c38df465c.js"],"component---src-templates-blog-tag-tsx":["cb1608f2-132bad9b5b9e5b660256.js","a9a7754c-940be9729966a77c2e4e.js","component---src-templates-blog-tag-tsx-f9e91ba073d8cbc40546.js"]},"childAssetsByChunkName":{}}